{"adult": 29, "air conditioner": 4, "aircraft": 49, "airplane": 15, "airplane fuel truck": 0, "airplanes": 5, "airport": 37, "american flag": 15, "animal": 67, "animals": 46, "antenna": 16, "apple": 112, "apples": 18, "appliance": 45, "apron": 130, "arch": 81, "archway": 3, "area": 401, "arm": 70, "arm rest": 0, "armrest": 3, "arms": 49, "arrow": 40, "arrows": 9, "art": 1005, "artwork": 96, "asphalt": 16, "audience": 3, "awning": 18, "baby": 66, "back": 618, "back door": 2, "back legs": 0, "background": 850, "backpack": 12, "bacon": 4, "bag": 103, "bags": 42, "balcony": 82, "ball": 406, "balloons": 6, "balls": 60, "banana": 36, "bananas": 5, "band": 315, "bandana": 0, "bank": 44, "banner": 26, "bar": 610, "bark": 1, "barn": 248, "barrel": 56, "barrier": 41, "barriers": 6, "bars": 192, "base": 435, "baseball": 14, "baseball player": 0, "baseboard": 0, "basket": 85, "bat": 14, "bathroom": 281, "bathtub": 35, "batter": 20, "beach": 118, "beads": 55, "beak": 1, "beam": 221, "beams": 309, "bean": 20, "beans": 22, "bear": 24, "bears": 24, "bed": 204, "bedding": 14, "bedroom": 281, "bedside lamp": 2, "bedspread": 0, "beer": 110, "bell": 42, "belly": 12, "belt": 96, "bench": 209, "benches": 66, "berries": 8, "bib": 0, "bicycle": 157, "bicycles": 56, "bike": 340, "biker": 55, "bikes": 179, "bikini": 4, "bill": 5, "billboard": 35, "bin": 43, "bird": 85, "birds": 44, "black": 1976, "blade": 140, "blades": 41, "blanket": 17, "bleachers": 0, "blender": 27, "blind": 16, "blinds": 20, "block": 173, "blocks": 63, "blouse": 3, "blue": 877, "board": 213, "boards": 41, "boat": 93, "boats": 34, "body": 269, "bolt": 82, "bolts": 97, "book": 146, "bookcase": 3, "books": 82, "bookshelf": 8, "boot": 29, "boots": 146, "border": 45, "bottle": 457, "bottles": 134, "bottom": 150, "bottoms": 6, "boulder": 6, "bow": 38, "bowl": 628, "bowls": 87, "box": 561, "box spring": 3, "boxes": 111, "boy": 70, "boy wearing mickey": 0, "boy's arm": 0, "boys": 84, "brace": 31, "bracelet": 680, "branch": 19, "branches": 18, "bread": 40, "brick": 264, "bricks": 28, "bride": 33, "bridge": 458, "bridle": 0, "broccoli": 10, "broccolli": 0, "brush": 85, "bubbles": 6, "bucket": 87, "bucket for tractor": 0, "building": 1230, "buildings": 363, "bull": 22, "bumper": 52, "bun": 0, "bunch": 10, "bunny": 8, "bus": 24, "buses": 5, "bush": 3, "bushes": 8, "butter": 50, "button": 39, "buttons": 23, "cab": 22, "cabbage": 5, "cabinet": 298, "cabinet door": 5, "cabinets": 391, "cable": 173, "cables": 74, "cake": 68, "calf": 12, "camera": 30, "camping trip": 1, "can": 1011, "candle": 37, "candles": 9, "candy": 17, "canister": 12, "canopies": 4, "canopy": 97, "cans": 37, "cap": 102, "caps": 58, "captain cookies van": 0, "car": 408, "card": 67, "cardboard": 9, "cargo shorts": 0, "carpet": 38, "carriage": 42, "carrot": 24, "carrots": 12, "cars": 242, "cart": 105, "carton": 4, "case": 626, "castle": 21, "cat": 99, "cat tail": 1, "catcher": 2, "cats": 23, "cattle": 23, "cauliflower": 2, "cave": 32, "cd": 6, "ceiling": 297, "cell phone": 11, "cellphone": 2, "cement": 67, "center": 274, "chain": 562, "chains": 61, "chair": 478, "chairs": 360, "chandelier": 58, "chapel": 6, "character": 79, "cheese": 56, "chemtrails": 0, "chest": 48, "chicken": 59, "child": 41, "children": 77, "chili": 16, "chin": 4, "chips": 31, "chocolate": 50, "church": 46, "circle": 107, "claw": 26, "claws": 7, "cleat": 3, "cleats": 1, "cliff": 8, "cliffs": 4, "clip": 133, "clock": 120, "clock face": 7, "clock tower": 3, "clocks": 35, "cloth": 55, "clothes": 52, "clothing": 37, "cloths": 0, "cloud": 25, "clouds": 15, "coaster": 53, "coat": 93, "cockpit": 2, "coffee": 452, "coffee table": 141, "coke": 43, "collar": 57, "color": 392, "color hair": 0, "column": 102, "columns": 109, "comforter": 0, "computer": 34, "computer screen": 1, "concrete": 792, "cone": 26, "cones": 4, "container": 197, "containers": 103, "controller": 5, "cookie": 21, "cooler": 47, "cord": 17, "cords": 2, "corn": 14, "corner": 163, "couch": 19, "counter": 207, "counter top": 31, "countertop": 89, "couple": 221, "couples": 33, "court": 54, "cover": 221, "covering": 33, "cow": 17, "cows": 8, "crack": 73, "cracks": 0, "crane": 117, "crate": 17, "cream": 110, "cross": 211, "crosswalk": 1, "crowd": 15, "crown": 104, "crullers": 0, "crumbs": 2, "crust": 8, "cucumber": 2, "cucumbers": 3, "cup": 268, "cupboard": 28, "cupcake": 4, "cups": 96, "curb": 33, "curtain": 88, "curtains": 29, "cushion": 27, "cushions": 58, "cutlery": 107, "cutting board": 32, "cycle": 17, "dark-haired": 0, "day": 290, "deck": 210, "decoration": 96, "deer": 20, "desert": 32, "design": 2664, "designs": 358, "desk": 255, "dessert": 18, "device": 42, "dining table": 214, "dinner": 55, "dirt": 22, "disc": 59, "dish": 100, "dishes": 78, "dishwasher": 79, "disk": 5, "disney princess": 2, "dispenser": 70, "display": 181, "divider": 11, "dock": 25, "dog": 211, "dogs": 65, "doll": 0, "dome": 91, "donkey": 2, "donut": 0, "donuts": 1, "door": 905, "door handle": 9, "door knob": 8, "doorknob": 1, "doors": 656, "doorway": 12, "dot": 23, "dough": 39, "doughnut": 2, "doughnuts": 4, "drain": 56, "drapes": 2, "drawer": 99, "drawers": 98, "drawing": 138, "dress": 88, "dresser": 17, "dresses": 30, "drink": 79, "driver": 30, "driveway": 72, "duck": 6, "ducks": 6, "dumpster": 2, "dwelling": 4, "ear": 95, "earring": 62, "ears": 12, "easel": 2, "edge": 204, "egg": 61, "eggs": 32, "elbow": 9, "elephant": 15, "elephants": 1, "emblem": 33, "enclosure": 30, "end": 312, "end table": 12, "engine": 138, "entrance": 177, "equipment": 267, "escalator": 7, "evergreen": 8, "exhaustion": 0, "eye": 125, "eyeglasses": 3, "eyes": 52, "fabric": 95, "face": 180, "family": 203, "fan": 72, "faucet": 250, "feather": 26, "feathers": 9, "feeder": 27, "feet": 160, "female": 74, "fence": 353, "fencing": 95, "fender": 52, "field": 97, "figurine": 1, "filter": 75, "finger": 96, "fingernail": 3, "fire": 376, "fire hydrant": 1, "fire truck": 2, "fireplace": 156, "fish": 64, "flag": 48, "flags": 16, "flame": 27, "flip flops": 0, "floor": 631, "floor mat": 1, "flooring": 226, "floors": 197, "flower": 80, "flower bed": 1, "flower pot": 2, "flowers": 52, "foam": 49, "foil": 9, "foliage": 8, "food": 334, "food truck": 6, "foot": 380, "footprints": 4, "forehead": 0, "forest": 47, "fork": 130, "fountain": 59, "fox": 28, "frame": 1481, "french fries": 3, "french fry": 2, "fridge": 93, "friend": 47, "fries": 7, "frisbee": 0, "front": 808, "front car": 0, "front leg": 0, "front tire": 0, "front wheel": 5, "front window": 3, "frosting": 9, "fruit": 57, "fruits": 20, "fry": 22, "fur": 18, "furniture": 724, "garage": 311, "garage floor": 4, "garbage can": 2, "garden": 574, "gate": 293, "giraffe": 1, "giraffes": 0, "girl": 84, "girls": 70, "glass": 1435, "glasses": 46, "glove": 6, "gloves": 24, "goat": 17, "goose": 1, "graffiti": 5, "grapes": 7, "graphic": 39, "grass": 46, "grate": 42, "grating": 39, "gravel": 32, "greenery": 15, "greens": 4, "grill": 238, "grooves": 8, "ground": 168, "group": 260, "guard": 82, "guy": 29, "hair": 86, "haircut": 7, "hand": 551, "handbag": 3, "handle": 343, "handle bars": 2, "handlebars": 6, "handles": 162, "handrail": 48, "hands": 150, "hanger": 50, "harness": 23, "hat": 33, "hatchback": 2, "hats": 11, "hawk": 5, "hay": 13, "head": 212, "head light": 0, "headband": 1, "headboard": 15, "headlight": 2, "headlights": 8, "headphones": 2, "heart": 203, "hedge": 12, "hedges": 0, "helmet": 123, "helmets": 29, "herd": 1, "highway": 19, "highway scaffolding": 0, "hill": 52, "hills": 23, "hillside": 24, "hinge": 42, "holder": 175, "hole": 235, "home": 1661, "home plate": 0, "hoodie": 6, "hook": 111, "hooves": 0, "horn": 50, "horns": 8, "horse": 98, "horse's head": 0, "horses": 37, "hose": 69, "hot dog": 1, "hot pack": 0, "hotdog": 0, "house": 1410, "houses": 153, "human": 45, "hydrant": 5, "icing": 6, "image": 833, "infield": 0, "intersection": 6, "item": 111, "items": 172, "jacket": 29, "jar": 68, "jean": 0, "jeans": 17, "jeep": 35, "jersey": 7, "jet": 27, "jockey": 2, "jug": 13, "juice": 19, "jump suit": 0, "kayak": 7, "ketchup": 3, "kettle": 100, "keyboard": 9, "keys": 27, "kid": 18, "kids": 145, "kitchen": 2206, "kite": 3, "kites": 0, "kitten": 8, "knee": 6, "knee pad": 0, "knees": 2, "knife": 232, "knob": 25, "knobs": 19, "label": 19, "lace": 30, "ladder": 99, "lady": 51, "lake": 58, "lamb": 2, "lamp": 181, "lamp post": 3, "lamp shade": 2, "lamppost": 0, "lamps": 73, "land": 84, "landscape": 142, "lantern": 30, "lanyard": 8, "laptop": 9, "lawn": 89, "lawn chair": 0, "leaf": 65, "leash": 6, "leaves": 36, "ledge": 15, "left ear": 0, "left hand": 3, "leg": 81, "legs": 230, "lemon": 29, "letter": 98, "lettering": 32, "letters": 51, "lettuce": 3, "lettuce, tomatoes": 0, "lid": 215, "lift": 81, "light": 726, "light fixture": 12, "light pole": 1, "light post": 0, "light shade": 0, "lighthouse": 3, "lighting": 288, "lights": 171, "limb": 2, "line": 261, "lines": 140, "linoleum": 3, "lion": 36, "lips": 6, "liquid": 51, "lock": 248, "log": 57, "logo": 277, "lot": 143, "luggage": 11, "m&m": 0, "machine": 405, "magazine": 70, "male": 140, "man": 621, "mane": 1, "manhole": 16, "manhole cover": 11, "mannequin": 2, "map": 48, "mark": 0, "marker": 11, "marking": 5, "markings": 13, "marks": 30, "mask": 29, "mat": 27, "material": 358, "mattress": 17, "meal": 21, "meat": 54, "median": 1, "men": 1295, "menu": 19, "meter": 24, "metrobus": 0, "microphone": 5, "microwave": 54, "mini van": 0, "minivan": 3, "mirror": 165, "mirrors": 24, "mist": 6, "mitt": 0, "molding": 18, "monitor": 9, "monkey": 8, "moped": 1, "moss": 7, "mother": 92, "mother elephant": 0, "motorbike": 3, "motorcycle": 76, "motorcycles": 43, "mound": 1, "mountain": 106, "mountain range": 3, "mountains": 27, "mouse": 16, "mouse pad": 0, "mousepad": 0, "mouth": 33, "mud": 29, "mug": 277, "mulch": 0, "mural of red paint": 0, "mushrooms": 10, "mustard": 7, "name": 158, "napkin": 16, "napkins": 2, "neck": 54, "necklace": 590, "necktie": 0, "net": 71, "netting": 25, "newspaper": 5, "nightstand": 1, "noodles": 22, "nose": 43, "notebook": 14, "number": 197, "numbers": 44, "numerals": 27, "nuts": 73, "oar": 0, "object": 22, "objects": 32, "ocean": 91, "officer": 15, "olive": 32, "olives": 1, "onion": 17, "onions": 19, "orange": 146, "oranges": 4, "ornament": 8, "ottoman": 29, "outfit": 33, "outlet": 49, "outside": 170, "oven": 158, "overpass": 9, "pack": 209, "package": 41, "packet": 0, "pad": 21, "paddle": 6, "pads": 36, "paint": 277, "painting": 135, "palm": 14, "palm tree": 4, "palm trees": 6, "pan": 184, "panda": 5, "pane": 3, "panel": 196, "panels": 329, "panes": 7, "pant": 0, "pants": 13, "paper": 92, "paper plate": 1, "papers": 24, "parade": 14, "parasail": 0, "parasol": 1, "park": 219, "parking lot": 17, "parking meter": 0, "part": 285, "partition": 21, "passenger": 14, "passengers": 7, "pasta": 37, "pastry": 14, "pasture": 4, "patch": 18, "path": 36, "pathway": 15, "patio": 253, "pattern": 243, "pavement": 7, "paw": 9, "paws": 1, "peak": 19, "peaks": 3, "pear": 6, "pedal": 42, "pedestrian": 42, "peel": 70, "pen": 66, "pencil": 19, "people": 176, "pepper": 18, "pepperoni": 2, "peppers": 14, "person": 6160, "petal": 5, "petals": 3, "phone": 28, "photo": 1470, "photographing": 1, "pickle": 2, "picture": 184, "picture frame": 3, "pictures": 347, "pie": 35, "piece": 496, "pieces": 165, "pier": 72, "pile": 57, "pillar": 32, "pillars": 26, "pillow": 7, "pillows": 14, "pine tree": 0, "pineapple": 11, "pipe": 353, "pipes": 127, "pit bull": 1, "pitcher": 10, "pitching area": 0, "pizza": 51, "pizza server": 0, "place": 292, "placemat": 0, "plane": 13, "planes": 5, "plank": 43, "planks": 17, "plant": 329, "planter": 59, "plants": 93, "plastic": 322, "plate": 499, "plates": 137, "platform": 77, "player": 25, "players": 31, "plug": 34, "pocket": 70, "pole": 155, "poles": 42, "police officer": 4, "policeman": 1, "pond": 28, "pony": 14, "ponytail": 0, "pool": 172, "porch": 74, "portion": 19, "post": 154, "posten": 0, "poster": 85, "posts": 63, "pot": 220, "potato": 21, "potatoes": 9, "pots": 65, "power line": 3, "power lines": 3, "print": 94, "printer": 14, "produce": 26, "propeller": 5, "puddle": 0, "pumpkin": 24, "puppy": 12, "purse": 5, "quarry": 2, "quilt": 11, "rack": 321, "racket": 1, "racquet": 0, "raft": 2, "rail": 114, "railing": 96, "railings": 47, "railroad": 40, "rails": 80, "ramp": 25, "range": 289, "rare wheel": 0, "rear": 200, "rectangle": 15, "reflection": 29, "reflector": 9, "refrigerator": 116, "relish": 0, "remote": 16, "remote control": 3, "ribbon": 33, "rice": 59, "rider": 26, "right": 291, "right arm": 1, "right ear": 0, "right hand": 3, "right leg": 0, "rim": 64, "ring": 780, "ripple": 3, "ripples": 4, "river": 200, "riverbed": 0, "road": 237, "road sign": 1, "roadway": 6, "robe": 5, "rock": 128, "rocks": 36, "rod": 231, "roll": 119, "rolling bag": 0, "rolls": 61, "roman numerals": 5, "roof": 566, "room": 882, "rope": 115, "rose": 0, "roses": 10, "row": 66, "rug": 33, "run way": 0, "runway": 6, "rust": 217, "s": 3027, "saddle": 34, "salad": 17, "salmon": 12, "salt shaker": 1, "sand": 45, "sandwich": 11, "satchel": 0, "sauce": 48, "saucer": 3, "sausage": 7, "scale": 78, "scarf": 2, "scissors": 82, "scooter": 7, "screen": 146, "sculpture": 506, "sea": 103, "sea gulls": 0, "seagull": 2, "seat": 309, "seats": 45, "section": 114, "sectional": 15, "shade": 124, "shades": 61, "shadow": 44, "shadows": 25, "shaker": 85, "shape": 274, "shed": 373, "sheep": 5, "sheet": 318, "sheets": 64, "shelf": 203, "shelter": 25, "shelves": 228, "shepard": 0, "ship": 124, "shirt": 200, "shirts": 32, "shoe": 57, "shoes": 118, "shop": 455, "shore": 20, "shoreline": 4, "short": 91, "shorts": 5, "shower": 141, "shower curtain": 3, "shower doors": 4, "shrimp": 15, "shrub": 3, "shrubbery": 0, "shrubs": 10, "shutter": 21, "side": 457, "side of rock": 0, "sidewalk": 10, "siding": 105, "sign": 187, "sign post": 1, "signal": 4, "signboard": 0, "signs": 85, "silverware": 8, "sink": 609, "skate board": 1, "skate park": 4, "skateboard": 4, "skateboarder": 0, "skater": 1, "skater shoes": 0, "ski": 9, "ski pants": 0, "ski pole": 0, "ski poles": 0, "ski slope": 0, "skier": 1, "skiers": 0, "skies": 2, "skin": 68, "skirt": 17, "skis": 0, "skull": 123, "skull picture": 0, "sky": 205, "sky scrapers": 1, "skyline": 26, "slab": 72, "slat": 12, "sleeve": 43, "sleeves": 11, "slice": 40, "slices": 19, "slope": 7, "smile": 12, "smoke": 55, "sneaker": 4, "sneakers": 11, "snow": 42, "snowboard": 0, "snowboarder": 0, "soap": 32, "soap dish": 2, "soap dispenser": 12, "soccer ball": 0, "soccer player": 1, "sock": 5, "socket": 18, "socks": 6, "sofa": 85, "soil": 26, "someone": 25, "soup": 33, "space": 614, "spatula": 41, "speaker": 6, "spectator": 1, "spectators": 2, "spinach": 10, "spire": 2, "splash": 38, "spokes": 9, "spoon": 144, "spot": 31, "spots": 23, "spout": 12, "sprinkles": 1, "square": 380, "squares": 9, "squash": 2, "stabilizer": 5, "stadium": 37, "stage": 91, "stain": 24, "stair": 115, "staircase": 260, "stairs": 219, "stairway": 24, "stalk": 0, "stand": 260, "stands": 110, "star": 109, "station": 131, "station wagon": 4, "statue": 51, "steeple": 1, "steering wheel": 9, "stem": 31, "stems": 3, "step": 112, "steps": 63, "stick": 43, "sticker": 28, "stickers": 7, "sticks": 17, "stone": 301, "stones": 81, "stool": 58, "stop": 49, "stop light": 0, "stop sign": 0, "store": 267, "storefront": 3, "stove": 166, "strap": 335, "straps": 51, "straw": 102, "strawberries": 12, "strawberry": 19, "stream": 14, "street": 313, "street lamp": 3, "street light": 4, "street lighting": 1, "street lights": 3, "street sign": 0, "streetlight": 0, "string": 38, "strings": 45, "strip": 52, "stripe": 14, "stripes": 18, "stroller": 0, "structure": 890, "stuff": 156, "stuffed animal": 0, "sugar": 71, "suit": 80, "suitcase": 2, "suitcases": 2, "sun": 90, "sunglasses": 19, "sunlight": 14, "sunset": 41, "support": 211, "surf board": 0, "surface": 368, "surfboard": 2, "surfboards": 0, "surfer": 2, "surfers": 2, "surfing": 2, "suv": 13, "sweater": 7, "sweatshirt": 0, "swim trunks": 0, "switch": 28, "system": 369, "t": 485, "t shirt": 11, "t-shirt": 151, "table": 1163, "table cloth": 0, "table top": 91, "tablecloth": 3, "tables": 291, "tag": 113, "tail": 35, "tail feathers": 0, "tail light": 0, "tank": 209, "tank top": 3, "tanks": 78, "tape": 28, "tarmac": 1, "tarp": 5, "tattoo": 28, "taxi": 1, "tea candle holder": 0, "team": 103, "teapot": 18, "teddy bear": 1, "tee shirt": 3, "teenager": 2, "telephone": 12, "telephone pole": 0, "television": 15, "tennis ball": 0, "tennis court": 5, "tennis player": 0, "tennis racket": 0, "tennis shoe": 0, "tent": 24, "terrain": 36, "terrycloth": 0, "text": 88, "thigh": 2, "tie": 74, "tile": 115, "tile flooring": 11, "tiles": 121, "time": 347, "tip": 51, "tire": 47, "tires": 56, "title": 14, "toast": 5, "toddler": 11, "toilet": 75, "toilet seat": 3, "tomato": 18, "tomatoes": 15, "tongs": 29, "tongue": 22, "tool": 327, "toothbrush": 4, "toothpaste": 1, "toothpick": 0, "top": 1000, "topping": 16, "toppings": 3, "tour bus": 0, "towel": 73, "towel rack": 17, "towels": 19, "tower": 177, "toy": 48, "toy bear": 0, "toys": 93, "track": 95, "tracks": 44, "traffic": 35, "traffic light": 1, "traffic lights": 0, "traffic sign": 0, "traffic signal": 0, "trail": 31, "train": 91, "train car": 3, "train engine": 0, "train platform": 0, "train station": 12, "train track": 0, "train tracks": 8, "trains": 34, "trash": 44, "trash bin": 0, "trash bucket": 0, "trash can": 31, "trashcan": 2, "tray": 129, "tree": 190, "tree branch": 0, "tree branches": 3, "tree trunk": 3, "trees": 79, "triangle": 26, "trim": 43, "trouser": 0, "trousers": 2, "truck": 218, "trumpet": 0, "trunk": 24, "trunks": 3, "tub": 102, "tunnel": 45, "tusk": 1, "tv": 65, "twig": 1, "twigs": 1, "two dogs": 0, "two skiers": 0, "tyre": 25, "umbrella": 20, "umbrellas": 3, "umpire": 1, "uniform": 12, "urinal": 4, "utensil": 7, "utensils": 67, "utility pole": 2, "van": 35, "vanity": 45, "vase": 33, "vases": 8, "vegetable": 40, "vegetables": 48, "vegetation": 4, "veggies": 3, "vehicle": 86, "vehicles": 131, "vest": 25, "via": 64, "video games": 8, "view": 799, "vine": 12, "vines": 7, "visor": 2, "volkswagen": 12, "wake": 14, "walkway": 40, "wall": 1420, "wallpaper": 115, "walls": 352, "watch": 1474, "water": 957, "water bottle": 248, "water in scene": 0, "water source": 2, "watermelon": 3, "waters": 4, "wave": 46, "waves": 16, "weather": 218, "weed": 3, "weeds": 2, "wetsuit": 0, "wheel": 188, "wheels": 418, "whisker": 0, "whiskers": 0, "white": 1697, "window": 297, "window pane": 0, "window sill": 5, "windows": 560, "windshield": 6, "wine": 185, "wine glass": 9, "wing": 53, "wings": 30, "winter jacket": 2, "wipers": 0, "wire": 474, "wires": 51, "woman": 100, "women": 483, "wood": 1330, "woodland": 7, "woods": 45, "word": 265, "words": 28, "wrap": 38, "wrapper": 2, "wrist": 170, "wristband": 2, "writing": 48, "y patients": 0, "yacht": 50, "yard": 272, "zebra": 7, "zebras": 1, "zipper": 2}