{"adult": 100, "air conditioner": 9, "aircraft": 128, "airplane": 48, "airplane fuel truck": 0, "airplanes": 4, "airport": 109, "american flag": 6, "animal": 234, "animals": 293, "antenna": 17, "apple": 76, "apples": 11, "appliance": 9, "apron": 37, "arch": 17, "archway": 0, "area": 482, "arm": 92, "arm rest": 1, "armrest": 2, "arms": 82, "arrow": 26, "arrows": 8, "art": 1637, "artwork": 158, "asphalt": 24, "audience": 16, "awning": 16, "baby": 246, "back": 711, "back door": 6, "back legs": 1, "background": 1284, "backpack": 13, "bacon": 0, "bag": 143, "bags": 69, "balcony": 16, "ball": 99, "balloons": 4, "balls": 22, "banana": 17, "bananas": 3, "band": 100, "bandana": 3, "bank": 90, "banner": 60, "bar": 249, "bark": 8, "barn": 84, "barrel": 23, "barrier": 8, "barriers": 4, "bars": 46, "base": 380, "baseball": 29, "baseball player": 0, "baseboard": 0, "basket": 52, "bat": 5, "bathroom": 46, "bathtub": 2, "batter": 4, "beach": 353, "beads": 17, "beak": 3, "beam": 22, "beams": 13, "bean": 15, "beans": 11, "bear": 40, "bears": 11, "bed": 290, "bedding": 10, "bedroom": 137, "bedside lamp": 1, "bedspread": 1, "beer": 69, "bell": 34, "belly": 16, "belt": 93, "bench": 150, "benches": 10, "berries": 4, "bib": 2, "bicycle": 53, "bicycles": 13, "bike": 327, "biker": 7, "bikes": 51, "bikini": 8, "bill": 14, "billboard": 2, "bin": 7, "bird": 56, "birds": 47, "black": 720, "blade": 35, "blades": 19, "blanket": 8, "bleachers": 0, "blender": 5, "blind": 21, "blinds": 9, "block": 72, "blocks": 40, "blouse": 18, "blue": 502, "board": 240, "boards": 48, "boat": 148, "boats": 58, "body": 285, "bolt": 9, "bolts": 7, "book": 379, "bookcase": 10, "books": 206, "bookshelf": 6, "boot": 35, "boots": 73, "border": 47, "bottle": 74, "bottles": 25, "bottom": 109, "bottoms": 6, "boulder": 4, "bow": 24, "bowl": 42, "bowls": 11, "box": 438, "box spring": 0, "boxes": 95, "boy": 281, "boy wearing mickey": 0, "boy's arm": 0, "boys": 104, "brace": 1, "bracelet": 30, "branch": 43, "branches": 17, "bread": 38, "brick": 79, "bricks": 21, "bride": 24, "bridge": 99, "bridle": 2, "broccoli": 4, "broccolli": 0, "brush": 52, "bubbles": 19, "bucket": 48, "bucket for tractor": 0, "building": 769, "buildings": 99, "bull": 31, "bumper": 8, "bun": 5, "bunch": 14, "bunny": 11, "bus": 41, "buses": 7, "bush": 9, "bushes": 18, "butter": 31, "button": 68, "buttons": 27, "cab": 10, "cabbage": 3, "cabinet": 82, "cabinet door": 2, "cabinets": 60, "cable": 148, "cables": 57, "cake": 86, "calf": 15, "camera": 238, "camping trip": 2, "can": 1471, "candle": 20, "candles": 25, "candy": 27, "canister": 1, "canopies": 0, "canopy": 9, "cans": 3, "cap": 73, "caps": 11, "captain cookies van": 0, "car": 725, "card": 137, "cardboard": 29, "cargo shorts": 0, "carpet": 59, "carriage": 30, "carrot": 3, "carrots": 2, "cars": 227, "cart": 42, "carton": 5, "case": 286, "castle": 64, "cat": 181, "cat tail": 0, "catcher": 4, "cats": 34, "cattle": 62, "cauliflower": 2, "cave": 16, "cd": 58, "ceiling": 44, "cell phone": 29, "cellphone": 19, "cement": 25, "center": 453, "chain": 66, "chains": 8, "chair": 261, "chairs": 84, "chandelier": 17, "chapel": 11, "character": 783, "cheese": 17, "chemtrails": 0, "chest": 44, "chicken": 30, "child": 334, "children": 517, "chili": 5, "chin": 10, "chips": 26, "chocolate": 66, "church": 59, "circle": 66, "claw": 8, "claws": 0, "cleat": 0, "cleats": 2, "cliff": 9, "cliffs": 1, "clip": 54, "clock": 269, "clock face": 8, "clock tower": 6, "clocks": 30, "cloth": 23, "clothes": 179, "clothing": 156, "cloths": 1, "cloud": 65, "clouds": 22, "coaster": 12, "coat": 71, "cockpit": 8, "coffee": 654, "coffee table": 40, "coke": 3, "collar": 33, "color": 277, "color hair": 0, "column": 22, "columns": 13, "comforter": 0, "computer": 2726, "computer screen": 39, "concrete": 127, "cone": 6, "cones": 5, "container": 31, "containers": 12, "controller": 43, "cookie": 7, "cooler": 8, "cord": 26, "cords": 3, "corn": 21, "corner": 86, "couch": 108, "counter": 111, "counter top": 3, "countertop": 4, "couple": 288, "couples": 12, "court": 47, "cover": 179, "covering": 22, "cow": 21, "cows": 20, "crack": 20, "cracks": 0, "crane": 65, "crate": 6, "cream": 43, "cross": 98, "crosswalk": 1, "crowd": 29, "crown": 22, "crullers": 0, "crumbs": 0, "crust": 5, "cucumber": 2, "cucumbers": 0, "cup": 250, "cupboard": 8, "cupcake": 10, "cups": 22, "curb": 6, "curtain": 9, "curtains": 12, "cushion": 3, "cushions": 8, "cutlery": 4, "cutting board": 5, "cycle": 38, "dark-haired": 14, "day": 958, "deck": 92, "decoration": 54, "deer": 24, "desert": 51, "design": 2246, "designs": 340, "desk": 1691, "dessert": 17, "device": 70, "dining table": 24, "dinner": 35, "dirt": 23, "disc": 41, "dish": 14, "dishes": 20, "dishwasher": 23, "disk": 16, "disney princess": 17, "dispenser": 20, "display": 161, "divider": 4, "dock": 24, "dog": 1024, "dogs": 709, "doll": 39, "dome": 14, "donkey": 21, "donut": 4, "donuts": 1, "door": 168, "door handle": 5, "door knob": 0, "doorknob": 1, "doors": 89, "doorway": 7, "dot": 19, "dough": 21, "doughnut": 2, "doughnuts": 2, "drain": 8, "drapes": 1, "drawer": 50, "drawers": 44, "drawing": 544, "dress": 134, "dresser": 6, "dresses": 61, "drink": 61, "driver": 58, "driveway": 7, "duck": 25, "ducks": 6, "dumpster": 0, "dwelling": 5, "ear": 19, "earring": 3, "ears": 13, "easel": 24, "edge": 45, "egg": 29, "eggs": 18, "elbow": 8, "elephant": 46, "elephants": 11, "emblem": 9, "enclosure": 8, "end": 248, "end table": 10, "engine": 271, "entrance": 22, "equipment": 334, "escalator": 1, "evergreen": 5, "exhaustion": 7, "eye": 110, "eyeglasses": 25, "eyes": 94, "fabric": 72, "face": 256, "family": 518, "fan": 100, "faucet": 5, "feather": 5, "feathers": 1, "feeder": 4, "feet": 97, "female": 893, "fence": 41, "fencing": 8, "fender": 8, "field": 621, "figurine": 7, "filter": 49, "finger": 38, "fingernail": 0, "fire": 260, "fire hydrant": 1, "fire truck": 3, "fireplace": 63, "fish": 98, "flag": 44, "flags": 10, "flame": 23, "flip flops": 0, "floor": 338, "floor mat": 0, "flooring": 48, "floors": 54, "flower": 145, "flower bed": 3, "flower pot": 4, "flowers": 147, "foam": 14, "foil": 0, "foliage": 6, "food": 371, "food truck": 4, "foot": 85, "footprints": 0, "forehead": 3, "forest": 86, "fork": 17, "fountain": 20, "fox": 25, "frame": 240, "french fries": 1, "french fry": 0, "fridge": 74, "friend": 109, "fries": 5, "frisbee": 0, "front": 656, "front car": 0, "front leg": 0, "front tire": 0, "front wheel": 1, "front window": 0, "frosting": 1, "fruit": 69, "fruits": 21, "fry": 1, "fur": 17, "furniture": 305, "garage": 177, "garage floor": 0, "garbage can": 0, "garden": 616, "gate": 26, "giraffe": 3, "giraffes": 1, "girl": 937, "girls": 222, "glass": 349, "glasses": 234, "glove": 11, "gloves": 92, "goat": 12, "goose": 6, "graffiti": 24, "grapes": 4, "graphic": 260, "grass": 74, "grate": 0, "grating": 2, "gravel": 11, "greenery": 5, "greens": 3, "grill": 70, "grooves": 1, "ground": 135, "group": 1049, "guard": 47, "guy": 145, "hair": 219, "haircut": 12, "hand": 733, "handbag": 4, "handle": 103, "handle bars": 11, "handlebars": 4, "handles": 41, "handrail": 1, "hands": 549, "hanger": 5, "harness": 42, "hat": 200, "hatchback": 9, "hats": 39, "hawk": 10, "hay": 26, "head": 229, "head light": 0, "headband": 5, "headboard": 4, "headlight": 0, "headlights": 14, "headphones": 99, "heart": 141, "hedge": 6, "hedges": 3, "helmet": 108, "helmets": 18, "herd": 11, "highway": 25, "highway scaffolding": 0, "hill": 55, "hills": 18, "hillside": 7, "hinge": 5, "holder": 30, "hole": 64, "home": 2330, "home plate": 0, "hoodie": 24, "hook": 21, "hooves": 2, "horn": 19, "horns": 9, "horse": 125, "horse's head": 0, "horses": 130, "hose": 27, "hot dog": 1, "hot pack": 0, "hotdog": 0, "house": 745, "houses": 85, "human": 274, "hydrant": 3, "icing": 1, "image": 806, "infield": 2, "intersection": 12, "item": 97, "items": 120, "jacket": 70, "jar": 9, "jean": 0, "jeans": 27, "jeep": 23, "jersey": 14, "jet": 31, "jockey": 3, "jug": 7, "juice": 13, "jump suit": 0, "kayak": 4, "ketchup": 0, "kettle": 22, "keyboard": 169, "keys": 50, "kid": 80, "kids": 396, "kitchen": 512, "kite": 4, "kites": 2, "kitten": 6, "knee": 21, "knee pad": 0, "knees": 16, "knife": 23, "knob": 14, "knobs": 3, "label": 23, "lace": 18, "ladder": 67, "lady": 149, "lake": 96, "lamb": 0, "lamp": 116, "lamp post": 1, "lamp shade": 0, "lamppost": 0, "lamps": 25, "land": 132, "landscape": 190, "lantern": 9, "lanyard": 2, "laptop": 3584, "lawn": 43, "lawn chair": 0, "leaf": 29, "leash": 5, "leaves": 55, "ledge": 3, "left ear": 0, "left hand": 9, "leg": 58, "legs": 74, "lemon": 19, "letter": 62, "lettering": 47, "letters": 63, "lettuce": 2, "lettuce, tomatoes": 0, "lid": 31, "lift": 79, "light": 469, "light fixture": 2, "light pole": 1, "light post": 0, "light shade": 0, "lighthouse": 19, "lighting": 129, "lights": 180, "limb": 1, "line": 506, "lines": 104, "linoleum": 1, "lion": 37, "lips": 6, "liquid": 16, "lock": 53, "log": 39, "logo": 181, "lot": 305, "luggage": 18, "m&m": 0, "machine": 805, "magazine": 80, "male": 475, "man": 3005, "mane": 2, "manhole": 6, "manhole cover": 0, "mannequin": 12, "map": 83, "mark": 0, "marker": 16, "marking": 16, "markings": 9, "marks": 151, "mask": 142, "mat": 25, "material": 87, "mattress": 16, "meal": 34, "meat": 20, "median": 2, "men": 601, "menu": 26, "meter": 14, "metrobus": 0, "microphone": 43, "microwave": 16, "mini van": 5, "minivan": 2, "mirror": 35, "mirrors": 18, "mist": 3, "mitt": 0, "molding": 9, "monitor": 124, "monkey": 20, "moped": 9, "moss": 7, "mother": 216, "mother elephant": 0, "motorbike": 11, "motorcycle": 49, "motorcycles": 26, "mound": 1, "mountain": 168, "mountain range": 1, "mountains": 42, "mouse": 47, "mouse pad": 1, "mousepad": 0, "mouth": 24, "mud": 18, "mug": 44, "mulch": 2, "mural of red paint": 0, "mushrooms": 5, "mustard": 0, "name": 100, "napkin": 1, "napkins": 1, "neck": 48, "necklace": 18, "necktie": 1, "net": 33, "netting": 0, "newspaper": 33, "nightstand": 1, "noodles": 4, "nose": 27, "notebook": 181, "number": 353, "numbers": 117, "numerals": 21, "nuts": 18, "oar": 5, "object": 39, "objects": 75, "ocean": 86, "officer": 179, "olive": 19, "olives": 1, "onion": 2, "onions": 10, "orange": 106, "oranges": 1, "ornament": 5, "ottoman": 3, "outfit": 59, "outlet": 11, "outside": 275, "oven": 86, "overpass": 0, "pack": 61, "package": 30, "packet": 8, "pad": 34, "paddle": 6, "pads": 7, "paint": 205, "painting": 446, "palm": 30, "palm tree": 7, "palm trees": 6, "pan": 15, "panda": 11, "pane": 2, "panel": 121, "panels": 46, "panes": 1, "pant": 2, "pants": 34, "paper": 350, "paper plate": 0, "papers": 118, "parade": 11, "parasail": 0, "parasol": 0, "park": 372, "parking lot": 26, "parking meter": 0, "part": 520, "partition": 2, "passenger": 23, "passengers": 27, "pasta": 4, "pastry": 14, "pasture": 11, "patch": 11, "path": 31, "pathway": 1, "patio": 54, "pattern": 141, "pavement": 10, "paw": 17, "paws": 6, "peak": 23, "peaks": 3, "pear": 3, "pedal": 34, "pedestrian": 9, "peel": 2, "pen": 153, "pencil": 117, "people": 2076, "pepper": 4, "pepperoni": 0, "peppers": 4, "person": 10214, "petal": 6, "petals": 2, "phone": 481, "photo": 2178, "photographing": 12, "pickle": 0, "picture": 482, "picture frame": 2, "pictures": 434, "pie": 10, "piece": 267, "pieces": 120, "pier": 25, "pile": 48, "pillar": 5, "pillars": 4, "pillow": 5, "pillows": 7, "pine tree": 0, "pineapple": 1, "pipe": 58, "pipes": 8, "pit bull": 12, "pitcher": 4, "pitching area": 0, "pizza": 34, "pizza server": 0, "place": 319, "placemat": 0, "plane": 47, "planes": 13, "plank": 20, "planks": 7, "plant": 209, "planter": 6, "plants": 194, "plastic": 119, "plate": 95, "plates": 27, "platform": 70, "player": 74, "players": 60, "plug": 36, "pocket": 84, "pole": 39, "poles": 6, "police officer": 90, "policeman": 4, "pond": 24, "pony": 9, "ponytail": 3, "pool": 210, "porch": 28, "portion": 25, "post": 219, "posten": 0, "poster": 206, "posts": 15, "pot": 40, "potato": 17, "potatoes": 3, "pots": 24, "power line": 3, "power lines": 7, "print": 171, "printer": 59, "produce": 69, "propeller": 2, "puddle": 2, "pumpkin": 12, "puppy": 76, "purse": 7, "quarry": 33, "quilt": 39, "rack": 52, "racket": 0, "racquet": 1, "raft": 0, "rail": 29, "railing": 1, "railings": 2, "railroad": 25, "rails": 10, "ramp": 18, "range": 129, "rare wheel": 0, "rear": 129, "rectangle": 6, "reflection": 11, "reflector": 3, "refrigerator": 12, "relish": 0, "remote": 219, "remote control": 44, "ribbon": 26, "rice": 160, "rider": 8, "right": 360, "right arm": 1, "right ear": 0, "right hand": 10, "right leg": 2, "rim": 11, "ring": 59, "ripple": 1, "ripples": 0, "river": 124, "riverbed": 0, "road": 280, "road sign": 5, "roadway": 8, "robe": 10, "rock": 116, "rocks": 31, "rod": 29, "roll": 45, "rolling bag": 0, "rolls": 14, "roman numerals": 11, "roof": 206, "room": 1018, "rope": 48, "rose": 0, "roses": 13, "row": 57, "rug": 13, "run way": 0, "runway": 10, "rust": 44, "s": 3603, "saddle": 32, "salad": 21, "salmon": 10, "salt shaker": 0, "sand": 82, "sandwich": 11, "satchel": 2, "sauce": 6, "saucer": 7, "sausage": 2, "scale": 77, "scarf": 16, "scissors": 7, "scooter": 26, "screen": 398, "sculpture": 162, "sea": 141, "sea gulls": 0, "seagull": 0, "seat": 81, "seats": 36, "section": 77, "sectional": 4, "shade": 25, "shades": 25, "shadow": 15, "shadows": 12, "shaker": 5, "shape": 155, "shed": 36, "sheep": 59, "sheet": 104, "sheets": 35, "shelf": 51, "shelter": 35, "shelves": 77, "shepard": 1, "ship": 77, "shirt": 328, "shirts": 43, "shoe": 71, "shoes": 121, "shop": 576, "shore": 28, "shoreline": 6, "short": 107, "shorts": 27, "shower": 34, "shower curtain": 3, "shower doors": 0, "shrimp": 9, "shrub": 3, "shrubbery": 0, "shrubs": 3, "shutter": 7, "side": 377, "side of rock": 0, "sidewalk": 15, "siding": 8, "sign": 221, "sign post": 0, "signal": 14, "signboard": 15, "signs": 142, "silverware": 2, "sink": 39, "skate board": 0, "skate park": 0, "skateboard": 9, "skateboarder": 0, "skater": 1, "skater shoes": 0, "ski": 19, "ski pants": 0, "ski pole": 0, "ski poles": 0, "ski slope": 1, "skier": 2, "skiers": 0, "skies": 8, "skin": 63, "skirt": 24, "skis": 0, "skull": 32, "skull picture": 0, "sky": 143, "sky scrapers": 0, "skyline": 13, "slab": 15, "slat": 0, "sleeve": 69, "sleeves": 12, "slice": 11, "slices": 1, "slope": 15, "smile": 68, "smoke": 99, "sneaker": 5, "sneakers": 28, "snow": 99, "snowboard": 1, "snowboarder": 0, "soap": 22, "soap dish": 0, "soap dispenser": 0, "soccer ball": 0, "soccer player": 1, "sock": 8, "socket": 11, "socks": 17, "sofa": 147, "soil": 71, "someone": 122, "soup": 6, "space": 823, "spatula": 8, "speaker": 50, "spectator": 0, "spectators": 0, "spinach": 1, "spire": 2, "splash": 8, "spokes": 1, "spoon": 6, "spot": 33, "spots": 23, "spout": 1, "sprinkles": 4, "square": 188, "squares": 15, "squash": 1, "stabilizer": 1, "stadium": 23, "stage": 90, "stain": 15, "stair": 10, "staircase": 12, "stairs": 60, "stairway": 2, "stalk": 1, "stand": 173, "stands": 72, "star": 144, "station": 234, "station wagon": 0, "statue": 44, "steeple": 0, "steering wheel": 12, "stem": 27, "stems": 4, "step": 78, "steps": 69, "stick": 59, "sticker": 26, "stickers": 32, "sticks": 13, "stone": 120, "stones": 29, "stool": 18, "stop": 152, "stop light": 1, "stop sign": 6, "store": 209, "storefront": 1, "stove": 18, "strap": 80, "straps": 21, "straw": 21, "strawberries": 2, "strawberry": 20, "stream": 19, "street": 353, "street lamp": 0, "street light": 0, "street lighting": 1, "street lights": 1, "street sign": 0, "streetlight": 0, "string": 36, "strings": 16, "strip": 18, "stripe": 9, "stripes": 16, "stroller": 2, "structure": 106, "stuff": 140, "stuffed animal": 3, "sugar": 25, "suit": 231, "suitcase": 21, "suitcases": 0, "sun": 65, "sunglasses": 27, "sunlight": 32, "sunset": 105, "support": 277, "surf board": 0, "surface": 129, "surfboard": 4, "surfboards": 3, "surfer": 8, "surfers": 4, "surfing": 29, "suv": 5, "sweater": 28, "sweatshirt": 5, "swim trunks": 0, "switch": 53, "system": 407, "t": 979, "t shirt": 11, "t-shirt": 106, "table": 1548, "table cloth": 0, "table top": 9, "tablecloth": 1, "tables": 131, "tag": 16, "tail": 26, "tail feathers": 0, "tail light": 1, "tank": 91, "tank top": 9, "tanks": 11, "tape": 47, "tarmac": 1, "tarp": 1, "tattoo": 145, "taxi": 12, "tea candle holder": 0, "team": 1235, "teapot": 2, "teddy bear": 2, "tee shirt": 0, "teenager": 22, "telephone": 43, "telephone pole": 2, "television": 55, "tennis ball": 1, "tennis court": 2, "tennis player": 1, "tennis racket": 0, "tennis shoe": 0, "tent": 31, "terrain": 21, "terrycloth": 0, "text": 426, "thigh": 5, "tie": 48, "tile": 45, "tile flooring": 2, "tiles": 36, "time": 1127, "tip": 20, "tire": 22, "tires": 42, "title": 53, "toast": 6, "toddler": 64, "toilet": 28, "toilet seat": 0, "tomato": 8, "tomatoes": 4, "tongs": 4, "tongue": 3, "tool": 215, "toothbrush": 0, "toothpaste": 1, "toothpick": 1, "top": 667, "topping": 0, "toppings": 0, "tour bus": 0, "towel": 10, "towel rack": 1, "towels": 11, "tower": 106, "toy": 127, "toy bear": 0, "toys": 120, "track": 93, "tracks": 20, "traffic": 70, "traffic light": 2, "traffic lights": 4, "traffic sign": 0, "traffic signal": 2, "trail": 42, "train": 163, "train car": 7, "train engine": 1, "train platform": 1, "train station": 7, "train track": 4, "train tracks": 1, "trains": 43, "trash": 17, "trash bin": 0, "trash bucket": 0, "trash can": 3, "trashcan": 0, "tray": 49, "tree": 238, "tree branch": 1, "tree branches": 2, "tree trunk": 3, "trees": 122, "triangle": 17, "trim": 19, "trouser": 2, "trousers": 9, "truck": 193, "trumpet": 2, "trunk": 13, "trunks": 3, "tub": 13, "tunnel": 37, "tusk": 2, "tv": 200, "twig": 3, "twigs": 1, "two dogs": 6, "two skiers": 0, "tyre": 13, "umbrella": 14, "umbrellas": 0, "umpire": 5, "uniform": 162, "urinal": 0, "utensil": 0, "utensils": 8, "utility pole": 3, "van": 57, "vanity": 11, "vase": 17, "vases": 6, "vegetable": 44, "vegetables": 35, "vegetation": 6, "veggies": 0, "vehicle": 155, "vehicles": 112, "vest": 39, "via": 70, "video games": 35, "view": 863, "vine": 3, "vines": 9, "visor": 2, "volkswagen": 13, "wake": 17, "walkway": 12, "wall": 480, "wallpaper": 161, "walls": 98, "watch": 349, "water": 477, "water bottle": 11, "water in scene": 0, "water source": 1, "watermelon": 4, "waters": 14, "wave": 19, "waves": 17, "weather": 55, "weed": 13, "weeds": 7, "wetsuit": 0, "wheel": 157, "wheels": 230, "whisker": 0, "whiskers": 0, "white": 1235, "window": 279, "window pane": 1, "window sill": 0, "windows": 124, "windshield": 5, "wine": 56, "wine glass": 8, "wing": 57, "wings": 18, "winter jacket": 0, "wipers": 3, "wire": 92, "wires": 60, "woman": 3345, "women": 842, "wood": 652, "woodland": 8, "woods": 34, "word": 143, "words": 95, "wrap": 22, "wrapper": 4, "wrist": 32, "wristband": 0, "writing": 405, "y patients": 0, "yacht": 15, "yard": 98, "zebra": 6, "zebras": 3, "zipper": 7}