{"airplane": 156, "apple": 305, "backpack": 203, "banana": 168, "baseball bat": 10, "baseball glove": 1, "bear": 274, "bed": 1575, "bench": 358, "bicycle": 183, "bird": 674, "boat": 341, "book": 1170, "bottle": 645, "bowl": 663, "broccoli": 54, "bus": 190, "cake": 916, "car": 1805, "carrot": 81, "cat": 727, "cell phone": 33, "chair": 984, "clock": 374, "couch": 404, "cow": 105, "cup": 673, "dining table": 496, "dog": 720, "donut": 57, "elephant": 129, "fire hydrant": 4, "fork": 100, "frisbee": 0, "giraffe": 52, "hair drier": 0, "handbag": 37, "horse": 367, "hot dog": 8, "keyboard": 84, "kite": 49, "knife": 96, "laptop": 296, "microwave": 54, "motorcycle": 235, "mouse": 91, "orange": 3399, "oven": 157, "parking meter": 1, "person": 28987, "pizza": 120, "potted plant": 19, "refrigerator": 65, "remote": 247, "sandwich": 74, "scissors": 36, "sheep": 95, "sink": 343, "skateboard": 54, "skis": 10, "snowboard": 9, "spoon": 128, "sports ball": 1, "stop sign": 20, "suitcase": 48, "surfboard": 27, "teddy bear": 95, "tennis racket": 5, "tie": 515, "toaster": 16, "toilet": 175, "toothbrush": 11, "traffic light": 577, "train": 639, "truck": 398, "tv": 503, "umbrella": 218, "vase": 390, "wine glass": 55, "zebra": 67}